dashai_image_classification_package/__init__.py
dashai_image_classification_package/image_dataloader.py
dashai_image_classification_package/mlp_image_classifier.py
dashai_image_classification_package-0.0.3.dist-info/METADATA
dashai_image_classification_package-0.0.3.dist-info/WHEEL
dashai_image_classification_package-0.0.3.dist-info/entry_points.txt
dashai_image_classification_package-0.0.3.dist-info/RECORD
