Metadata-Version: 2.4
Name: dashai_image_classification_package
Version: 0.0.3
Summary: Image Classification Plugin for DashAI
Project-URL: Homepage, https://github.com/DashAISoftware/DashAI
Project-URL: Issues, https://github.com/DashAISoftware/DashAI/issues
Author: DashAI team
Author-email: dashaisoftware@gmail.com
Keywords: DashAI,Dataloader,Model
Requires-Python: >=3.10
Requires-Dist: torchvision==0.19.1
